{
  "kind": "anime-film",
  "title": "Cowboy Bebop: Tengoku no Tobira",
  "main_page_title": "Cowboy Bebop: The Movie",
  "main_page_extract": "Cowboy Bebop: The Movie (Japanese: カウボーイビバップ 天国の扉, Hepburn: Kaubōi Bibappu Tengoku no Tobira; lit. 'Cowboy Bebop: Heaven's Door') is a 2001 Japanese anime science fiction action film, based on the 1998 anime series Cowboy Bebop created by Sunrise and Hajime Yatate. Several staff from the original series returned to work on the film, including director Shinichirō Watanabe, writer Keiko Nobumoto, character designer and animation director Toshihiro Kawamoto and composer Yoko Kanno. The Japanese and English voice casts also reprised their roles. Set between episodes 22 and 23 of the original series, the plot centers on a mysterious terrorist planning to exterminate the human population of Mars by releasing a virus, with the bounty hunter crew of the spaceship Bebop working to capture the terrorist and prevent the attack.\nThe film was conceived by Watanabe as an extension of his work on the television series, in which he had treated each episode as a miniature film. As not to alienate existing fans, much of the series' style was retained, with adjustments to make it accessible to a wider audience. Increased budget and production facilities enabled filming styles associated with live action...",
  "character_page_title": null,
  "character_page_extract": ""
}