{
  "kind": "anime-film",
  "title": "City Hunter: Bay City Wars",
  "main_page_title": "City Hunter",
  "main_page_extract": "City Hunter (Japanese: シティーハンター, Hepburn: Shitī Hantā) is a Japanese manga series written and illustrated by Tsukasa Hojo. It was serialized in Shueisha's shōnen manga magazine Weekly Shōnen Jump from 1985 to 1991, with its chapters collected in 35 tankōbon volumes. The manga was adapted into an anime television series by Sunrise Studios in 1987. The anime series was popular in numerous Asian and European countries.\nCity Hunter spawned a media franchise consisting of numerous adaptations and spin-offs from several countries. The franchise includes four anime television series, three anime television specials, three made-for-television animated films, two animated feature films for theatrical release (Shinjuku Private Eyes in February 2019 and Angel Dust in September 2023), several live-action films (including City Hunter, a Hong Kong film starring Jackie Chan, and Nicky Larson et le Parfum de Cupidon, a French film), video games, and a live-action Korean TV drama. It also had a spin-off manga, Angel Heart, which in turn spawned its own anime television series and a live-action Japanese TV drama.\n\n\n== Plot ==\nThe series follows the exploits of Ryo Saeba, a \"sweeper\" who is always found...",
  "character_page_title": null,
  "character_page_extract": ""
}