{
  "kind": "anime-film",
  "title": "Kidou Senshi Gundam II: Ai Senshi-hen",
  "main_page_title": "List of Wii games",
  "main_page_extract": "The Wii is Nintendo's fifth home video game console, released during the seventh generation of video games. It is the successor to the GameCube, and was first launched in North America on November 19, 2006, followed by a launch in Japan and PAL regions in December 2006.\nThis list of Wii games documents all games released for the Wii video game console. The list of GameCube games lists the GameCube games compatible with the Wii’s backwards compatibility (although later Wii models removed the controller ports and memory card slots required to play GameCube games, they can be inserted back in through hardware modding) while the list of WiiWare games documents all of the smaller, digital only games released for the Wii. Any games originally released for other platforms that were re-released games under the Virtual Console banner are additionally documented at the List of Virtual Console games lists. Games that were announced or reported to be in development for the Wii, but never released, are documented at the list of cancelled Wii games list.\nOn November 19, 2006, the Wii launch was accompanied by 20 launch games. The last game releases for the Wii, Retro City Rampage DX+ and Shakedown...",
  "character_page_title": null,
  "character_page_extract": ""
}