{
  "kind": "anime-film",
  "title": "Touch: Sebangou no Nai Ace",
  "main_page_title": "Yūji Mitsuya",
  "main_page_extract": "Yūji Mitsuya (三ツ矢 雄二, Mitsuya Yūji; born October 18, 1954) is a Japanese actor, voice actor, director of audiography, voice director, and sound supervisor from Toyohashi, Aichi Prefecture who is affiliated with Mitsuya Project. He graduated from Meiji University.\nHe is best known for his roles in The Lion King as Timon, Touch as Tatsuya Uesugi, Combattler V as Hyōma Aoi, Kiteretsu Daihyakka as Kōji Togari, Saint Seiya as Virgo Shaka, and the TV Asahi version of the Japanese dub of the Back to the Future trilogy as Marty McFly.\nMitsuya came out as gay on a TV show on January 12, 2017. In January 2022, Mitsuya revealed that he had been diagnosed with prostate cancer in January 2021.\n\n\n== Filmography ==\n\n\n=== Television animation ===\nCandy Candy (1976) as Archibald \"Archie\" Cornwell\nCombattler V (1976) (Hyoma Aoi)\nSasuga no Sarutobi (1982) (Sarutobi Nikumaru)\nCaptain Tsubasa (1983) (Shun Nitta)\nGeorgie! (1983) (Lowell J. Gray) (Royal)\nNanako SOS (1983) (Tomoshige Yotsuya)\nSerendipity the Pink Dragon (1983) (Pira Pira)\nChoriki Robo Galatt (1984) (Saradaayu)\nGlass no Kamen (1984 TV series) (1984) (Sakurakouji Yuu)\nTouch (1985) (Tatsuya Uesugi)\nSaint Seiya (1986) (Virgo Shaka)\nSaint Seiya (1988...",
  "character_page_title": null,
  "character_page_extract": ""
}