{
  "kind": "game",
  "title": "Bendy",
  "main_page_title": "Bendy and the Ink Machine",
  "main_page_extract": "Bendy and the Ink Machine is an episodic survival horror game developed and published by Joey Drew Studios. It was initially released to Game Jolt on February 10, 2017, as the first of five chapters, with a full worldwide release on October 27, 2018. The game was also released for PlayStation 4, Xbox One, and Nintendo Switch on November 20, 2018, being published by Rooster Teeth Games, for iOS and Android on December 21, 2018, and for PlayStation 5, and Xbox Series X/S on May 9, 2025.\nInspired by the BioShock game series, the game is set in the fictional Joey Drew Studios. The player controls Henry Stein, a retired animator who receives a letter inviting him \nback to his old workplace. Stein discovers a series of strange paranormal activities caused by the titular Ink Machine. In the game, players navigate through a first person perspective and need to complete certain tasks to proceed, such as combat, collecting objects, or solving puzzles. Players can also find audio logs recorded by the studio's employees to understand the game's history.\nBendy and the Ink Machine was well-received upon its initial release. Praise centered on its vintage aesthetic and story, although its puzzles...",
  "character_page_title": null,
  "character_page_extract": ""
}